proxlist/__init__.py
proxlist/_version.py
proxlist/proxies.py
proxlist/py.typed
proxlist-2.0.0.dist-info/licenses/LICENSE
proxlist-2.0.0.dist-info/METADATA
proxlist-2.0.0.dist-info/WHEEL
proxlist-2.0.0.dist-info/top_level.txt
proxlist-2.0.0.dist-info/RECORD
